pytocron/__init__.py
pytocron/__main__.py
pytocron/_crontab_parser.py
pytocron/_logging.py
pytocron/_main.py
pytocron/_runner.py
pytocron/_timing.py
pytocron/_version.py
pytocron/tests/__init__.py
pytocron/tests/test_crontab_parser.py
pytocron/tests/test_daylight_saving.py
pytocron/tests/test_main.py
pytocron/tests/test_runner.py
pytocron/tests/test_timing.py
pytocron-2.0.0.dist-info/METADATA
pytocron-2.0.0.dist-info/WHEEL
pytocron-2.0.0.dist-info/entry_points.txt
pytocron-2.0.0.dist-info/licenses/COPYING
pytocron-2.0.0.dist-info/RECORD
