Metadata-Version: 2.4
Name: pytocron
Version: 2.0.0
Summary: Container cron with seconds resolution
Project-URL: Homepage, https://github.com/hartwork/pytocron
Author-email: Sebastian Pipping <sebastian@pipping.org>
License: AGPL-3.0-or-later
License-File: COPYING
Keywords: automation,cron
Classifier: Development Status :: 4 - Beta
Classifier: Programming Language :: Python
Classifier: Programming Language :: Python :: 3
Classifier: Programming Language :: Python :: 3 :: Only
Classifier: Programming Language :: Python :: 3.10
Classifier: Programming Language :: Python :: 3.11
Classifier: Programming Language :: Python :: 3.12
Classifier: Programming Language :: Python :: 3.13
Classifier: Programming Language :: Python :: Implementation :: CPython
Requires-Python: >=3.10
Requires-Dist: colorama
Requires-Dist: croniter
Requires-Dist: requests
Provides-Extra: tests
Requires-Dist: coverage; extra == 'tests'
Requires-Dist: parameterized; extra == 'tests'
Requires-Dist: pytest; extra == 'tests'
Requires-Dist: pytz; extra == 'tests'
Requires-Dist: sentry-sdk; extra == 'tests'
